{
  "__meta": {
    "storyKey": "T6-9",
    "regenerated": null,
    "scoreNotes": "Deterministically generated by pinehurst-hand-calc-generator.mjs. Scores tuned for plausibility + rule coverage. Re-generate by editing constants in the .mjs file and re-running it.",
    "scoreIntentByHole": [
      {
        "round": 1,
        "hole": 1,
        "kind": "skin",
        "note": "P1 birdie (3) on par 4; sole sub-par → gross-mode skin to P1"
      },
      {
        "round": 1,
        "hole": 6,
        "kind": "best-ball-low",
        "note": "P1 birdie (2) on par 3; team A advantage"
      },
      {
        "round": 1,
        "hole": 13,
        "kind": "skin",
        "note": "P1 birdie (3) on par 4; potential skin"
      },
      {
        "round": 2,
        "hole": 9,
        "kind": "skin",
        "note": "P1 birdie (3) on par 4"
      },
      {
        "round": 2,
        "hole": 11,
        "kind": "skin-tie",
        "note": "P1 par + P4 birdie on par 5 → P4 has lowest gross, but check vs others"
      },
      {
        "round": 2,
        "hole": 17,
        "kind": "skin",
        "note": "P1 birdie (2) on par 3"
      },
      {
        "round": 3,
        "hole": 5,
        "kind": "skin",
        "note": "P1 birdie (4) on par 5"
      },
      {
        "round": 3,
        "hole": 13,
        "kind": "skin-tie-carry",
        "note": "P2 birdie + P3 birdie on par 4 → tie; skin carries to hole 14"
      },
      {
        "round": 4,
        "hole": 3,
        "kind": "skin",
        "note": "P1 birdie (3) on par 4"
      },
      {
        "round": 4,
        "hole": 11,
        "kind": "skin",
        "note": "P1 birdie (4) + P4 birdie (4) on par 5 — both 4s; tie-carry"
      },
      {
        "round": 1,
        "hole": 3,
        "kind": "bet1-stroke",
        "note": "P4 receives 2 strokes (CH 22, SI 1); affects P1 vs P4 net comparison"
      },
      {
        "round": 2,
        "hole": 3,
        "kind": "bet1+bet2",
        "note": "P3 receives stroke (CH 14, SI 1); affects both bets"
      }
    ]
  },
  "course": {
    "tee": {
      "slope": 113,
      "ratingTimes10": 720,
      "coursePar": 72
    },
    "holes": [
      {
        "holeNumber": 1,
        "par": 4,
        "strokeIndex": 5
      },
      {
        "holeNumber": 2,
        "par": 5,
        "strokeIndex": 11
      },
      {
        "holeNumber": 3,
        "par": 4,
        "strokeIndex": 1
      },
      {
        "holeNumber": 4,
        "par": 4,
        "strokeIndex": 9
      },
      {
        "holeNumber": 5,
        "par": 5,
        "strokeIndex": 13
      },
      {
        "holeNumber": 6,
        "par": 3,
        "strokeIndex": 17
      },
      {
        "holeNumber": 7,
        "par": 4,
        "strokeIndex": 3
      },
      {
        "holeNumber": 8,
        "par": 3,
        "strokeIndex": 15
      },
      {
        "holeNumber": 9,
        "par": 4,
        "strokeIndex": 7
      },
      {
        "holeNumber": 10,
        "par": 4,
        "strokeIndex": 6
      },
      {
        "holeNumber": 11,
        "par": 5,
        "strokeIndex": 12
      },
      {
        "holeNumber": 12,
        "par": 4,
        "strokeIndex": 2
      },
      {
        "holeNumber": 13,
        "par": 4,
        "strokeIndex": 10
      },
      {
        "holeNumber": 14,
        "par": 5,
        "strokeIndex": 14
      },
      {
        "holeNumber": 15,
        "par": 3,
        "strokeIndex": 18
      },
      {
        "holeNumber": 16,
        "par": 4,
        "strokeIndex": 4
      },
      {
        "holeNumber": 17,
        "par": 3,
        "strokeIndex": 16
      },
      {
        "holeNumber": 18,
        "par": 4,
        "strokeIndex": 8
      }
    ]
  },
  "players": [
    {
      "id": "P1",
      "name": "Player 1 (scratch)",
      "handicapIndex": 0
    },
    {
      "id": "P2",
      "name": "Player 2 (mid)",
      "handicapIndex": 8
    },
    {
      "id": "P3",
      "name": "Player 3 (mid-high)",
      "handicapIndex": 14
    },
    {
      "id": "P4",
      "name": "Player 4 (high)",
      "handicapIndex": 22
    }
  ],
  "rounds": [
    {
      "roundNumber": 1,
      "pairings": {
        "teamA": [
          "P1",
          "P2"
        ],
        "teamB": [
          "P3",
          "P4"
        ]
      },
      "holeScores": [
        {
          "playerId": "P1",
          "holeNumber": 1,
          "grossStrokes": 3,
          "putts": 2
        },
        {
          "playerId": "P2",
          "holeNumber": 1,
          "grossStrokes": 4,
          "putts": 2
        },
        {
          "playerId": "P3",
          "holeNumber": 1,
          "grossStrokes": 5,
          "putts": 2
        },
        {
          "playerId": "P4",
          "holeNumber": 1,
          "grossStrokes": 6,
          "putts": 2
        },
        {
          "playerId": "P1",
          "holeNumber": 2,
          "grossStrokes": 5,
          "putts": 2
        },
        {
          "playerId": "P2",
          "holeNumber": 2,
          "grossStrokes": 6,
          "putts": 2
        },
        {
          "playerId": "P3",
          "holeNumber": 2,
          "grossStrokes": 7,
          "putts": 2
        },
        {
          "playerId": "P4",
          "holeNumber": 2,
          "grossStrokes": 6,
          "putts": 2
        },
        {
          "playerId": "P1",
          "holeNumber": 3,
          "grossStrokes": 4,
          "putts": 2
        },
        {
          "playerId": "P2",
          "holeNumber": 3,
          "grossStrokes": 5,
          "putts": 2
        },
        {
          "playerId": "P3",
          "holeNumber": 3,
          "grossStrokes": 5,
          "putts": 2
        },
        {
          "playerId": "P4",
          "holeNumber": 3,
          "grossStrokes": 7,
          "putts": 2
        },
        {
          "playerId": "P1",
          "holeNumber": 4,
          "grossStrokes": 4,
          "putts": 2
        },
        {
          "playerId": "P2",
          "holeNumber": 4,
          "grossStrokes": 4,
          "putts": 2
        },
        {
          "playerId": "P3",
          "holeNumber": 4,
          "grossStrokes": 6,
          "putts": 2
        },
        {
          "playerId": "P4",
          "holeNumber": 4,
          "grossStrokes": 4,
          "putts": 2
        },
        {
          "playerId": "P1",
          "holeNumber": 5,
          "grossStrokes": 5,
          "putts": 2
        },
        {
          "playerId": "P2",
          "holeNumber": 5,
          "grossStrokes": 6,
          "putts": 2
        },
        {
          "playerId": "P3",
          "holeNumber": 5,
          "grossStrokes": 6,
          "putts": 2
        },
        {
          "playerId": "P4",
          "holeNumber": 5,
          "grossStrokes": 7,
          "putts": 2
        },
        {
          "playerId": "P1",
          "holeNumber": 6,
          "grossStrokes": 2,
          "putts": 2
        },
        {
          "playerId": "P2",
          "holeNumber": 6,
          "grossStrokes": 3,
          "putts": 2
        },
        {
          "playerId": "P3",
          "holeNumber": 6,
          "grossStrokes": 4,
          "putts": 2
        },
        {
          "playerId": "P4",
          "holeNumber": 6,
          "grossStrokes": 5,
          "putts": 2
        },
        {
          "playerId": "P1",
          "holeNumber": 7,
          "grossStrokes": 4,
          "putts": 2
        },
        {
          "playerId": "P2",
          "holeNumber": 7,
          "grossStrokes": 5,
          "putts": 2
        },
        {
          "playerId": "P3",
          "holeNumber": 7,
          "grossStrokes": 5,
          "putts": 2
        },
        {
          "playerId": "P4",
          "holeNumber": 7,
          "grossStrokes": 6,
          "putts": 2
        },
        {
          "playerId": "P1",
          "holeNumber": 8,
          "grossStrokes": 3,
          "putts": 2
        },
        {
          "playerId": "P2",
          "holeNumber": 8,
          "grossStrokes": 4,
          "putts": 2
        },
        {
          "playerId": "P3",
          "holeNumber": 8,
          "grossStrokes": 4,
          "putts": 2
        },
        {
          "playerId": "P4",
          "holeNumber": 8,
          "grossStrokes": 4,
          "putts": 2
        },
        {
          "playerId": "P1",
          "holeNumber": 9,
          "grossStrokes": 4,
          "putts": 2
        },
        {
          "playerId": "P2",
          "holeNumber": 9,
          "grossStrokes": 5,
          "putts": 2
        },
        {
          "playerId": "P3",
          "holeNumber": 9,
          "grossStrokes": 6,
          "putts": 2
        },
        {
          "playerId": "P4",
          "holeNumber": 9,
          "grossStrokes": 7,
          "putts": 2
        },
        {
          "playerId": "P1",
          "holeNumber": 10,
          "grossStrokes": 4,
          "putts": 2
        },
        {
          "playerId": "P2",
          "holeNumber": 10,
          "grossStrokes": 4,
          "putts": 2
        },
        {
          "playerId": "P3",
          "holeNumber": 10,
          "grossStrokes": 5,
          "putts": 2
        },
        {
          "playerId": "P4",
          "holeNumber": 10,
          "grossStrokes": 6,
          "putts": 2
        },
        {
          "playerId": "P1",
          "holeNumber": 11,
          "grossStrokes": 5,
          "putts": 2
        },
        {
          "playerId": "P2",
          "holeNumber": 11,
          "grossStrokes": 5,
          "putts": 2
        },
        {
          "playerId": "P3",
          "holeNumber": 11,
          "grossStrokes": 6,
          "putts": 2
        },
        {
          "playerId": "P4",
          "holeNumber": 11,
          "grossStrokes": 7,
          "putts": 2
        },
        {
          "playerId": "P1",
          "holeNumber": 12,
          "grossStrokes": 4,
          "putts": 2
        },
        {
          "playerId": "P2",
          "holeNumber": 12,
          "grossStrokes": 5,
          "putts": 2
        },
        {
          "playerId": "P3",
          "holeNumber": 12,
          "grossStrokes": 5,
          "putts": 2
        },
        {
          "playerId": "P4",
          "holeNumber": 12,
          "grossStrokes": 6,
          "putts": 2
        },
        {
          "playerId": "P1",
          "holeNumber": 13,
          "grossStrokes": 3,
          "putts": 2
        },
        {
          "playerId": "P2",
          "holeNumber": 13,
          "grossStrokes": 5,
          "putts": 2
        },
        {
          "playerId": "P3",
          "holeNumber": 13,
          "grossStrokes": 6,
          "putts": 2
        },
        {
          "playerId": "P4",
          "holeNumber": 13,
          "grossStrokes": 7,
          "putts": 2
        },
        {
          "playerId": "P1",
          "holeNumber": 14,
          "grossStrokes": 5,
          "putts": 2
        },
        {
          "playerId": "P2",
          "holeNumber": 14,
          "grossStrokes": 6,
          "putts": 2
        },
        {
          "playerId": "P3",
          "holeNumber": 14,
          "grossStrokes": 6,
          "putts": 2
        },
        {
          "playerId": "P4",
          "holeNumber": 14,
          "grossStrokes": 7,
          "putts": 2
        },
        {
          "playerId": "P1",
          "holeNumber": 15,
          "grossStrokes": 3,
          "putts": 2
        },
        {
          "playerId": "P2",
          "holeNumber": 15,
          "grossStrokes": 4,
          "putts": 2
        },
        {
          "playerId": "P3",
          "holeNumber": 15,
          "grossStrokes": 4,
          "putts": 2
        },
        {
          "playerId": "P4",
          "holeNumber": 15,
          "grossStrokes": 4,
          "putts": 2
        },
        {
          "playerId": "P1",
          "holeNumber": 16,
          "grossStrokes": 4,
          "putts": 2
        },
        {
          "playerId": "P2",
          "holeNumber": 16,
          "grossStrokes": 5,
          "putts": 2
        },
        {
          "playerId": "P3",
          "holeNumber": 16,
          "grossStrokes": 6,
          "putts": 2
        },
        {
          "playerId": "P4",
          "holeNumber": 16,
          "grossStrokes": 6,
          "putts": 2
        },
        {
          "playerId": "P1",
          "holeNumber": 17,
          "grossStrokes": 3,
          "putts": 2
        },
        {
          "playerId": "P2",
          "holeNumber": 17,
          "grossStrokes": 4,
          "putts": 2
        },
        {
          "playerId": "P3",
          "holeNumber": 17,
          "grossStrokes": 4,
          "putts": 2
        },
        {
          "playerId": "P4",
          "holeNumber": 17,
          "grossStrokes": 5,
          "putts": 2
        },
        {
          "playerId": "P1",
          "holeNumber": 18,
          "grossStrokes": 4,
          "putts": 2
        },
        {
          "playerId": "P2",
          "holeNumber": 18,
          "grossStrokes": 5,
          "putts": 2
        },
        {
          "playerId": "P3",
          "holeNumber": 18,
          "grossStrokes": 6,
          "putts": 2
        },
        {
          "playerId": "P4",
          "holeNumber": 18,
          "grossStrokes": 7,
          "putts": 2
        }
      ],
      "holeMeta": []
    },
    {
      "roundNumber": 2,
      "pairings": {
        "teamA": [
          "P1",
          "P3"
        ],
        "teamB": [
          "P2",
          "P4"
        ]
      },
      "holeScores": [
        {
          "playerId": "P1",
          "holeNumber": 1,
          "grossStrokes": 4,
          "putts": 2
        },
        {
          "playerId": "P2",
          "holeNumber": 1,
          "grossStrokes": 5,
          "putts": 2
        },
        {
          "playerId": "P3",
          "holeNumber": 1,
          "grossStrokes": 5,
          "putts": 2
        },
        {
          "playerId": "P4",
          "holeNumber": 1,
          "grossStrokes": 6,
          "putts": 2
        },
        {
          "playerId": "P1",
          "holeNumber": 2,
          "grossStrokes": 5,
          "putts": 2
        },
        {
          "playerId": "P2",
          "holeNumber": 2,
          "grossStrokes": 6,
          "putts": 2
        },
        {
          "playerId": "P3",
          "holeNumber": 2,
          "grossStrokes": 6,
          "putts": 2
        },
        {
          "playerId": "P4",
          "holeNumber": 2,
          "grossStrokes": 7,
          "putts": 2
        },
        {
          "playerId": "P1",
          "holeNumber": 3,
          "grossStrokes": 4,
          "putts": 2
        },
        {
          "playerId": "P2",
          "holeNumber": 3,
          "grossStrokes": 4,
          "putts": 2
        },
        {
          "playerId": "P3",
          "holeNumber": 3,
          "grossStrokes": 3,
          "putts": 2
        },
        {
          "playerId": "P4",
          "holeNumber": 3,
          "grossStrokes": 6,
          "putts": 2
        },
        {
          "playerId": "P1",
          "holeNumber": 4,
          "grossStrokes": 4,
          "putts": 2
        },
        {
          "playerId": "P2",
          "holeNumber": 4,
          "grossStrokes": 5,
          "putts": 2
        },
        {
          "playerId": "P3",
          "holeNumber": 4,
          "grossStrokes": 6,
          "putts": 2
        },
        {
          "playerId": "P4",
          "holeNumber": 4,
          "grossStrokes": 6,
          "putts": 2
        },
        {
          "playerId": "P1",
          "holeNumber": 5,
          "grossStrokes": 5,
          "putts": 2
        },
        {
          "playerId": "P2",
          "holeNumber": 5,
          "grossStrokes": 6,
          "putts": 2
        },
        {
          "playerId": "P3",
          "holeNumber": 5,
          "grossStrokes": 7,
          "putts": 2
        },
        {
          "playerId": "P4",
          "holeNumber": 5,
          "grossStrokes": 7,
          "putts": 2
        },
        {
          "playerId": "P1",
          "holeNumber": 6,
          "grossStrokes": 3,
          "putts": 2
        },
        {
          "playerId": "P2",
          "holeNumber": 6,
          "grossStrokes": 4,
          "putts": 2
        },
        {
          "playerId": "P3",
          "holeNumber": 6,
          "grossStrokes": 4,
          "putts": 2
        },
        {
          "playerId": "P4",
          "holeNumber": 6,
          "grossStrokes": 5,
          "putts": 2
        },
        {
          "playerId": "P1",
          "holeNumber": 7,
          "grossStrokes": 4,
          "putts": 2
        },
        {
          "playerId": "P2",
          "holeNumber": 7,
          "grossStrokes": 5,
          "putts": 2
        },
        {
          "playerId": "P3",
          "holeNumber": 7,
          "grossStrokes": 6,
          "putts": 2
        },
        {
          "playerId": "P4",
          "holeNumber": 7,
          "grossStrokes": 6,
          "putts": 2
        },
        {
          "playerId": "P1",
          "holeNumber": 8,
          "grossStrokes": 3,
          "putts": 2
        },
        {
          "playerId": "P2",
          "holeNumber": 8,
          "grossStrokes": 4,
          "putts": 2
        },
        {
          "playerId": "P3",
          "holeNumber": 8,
          "grossStrokes": 4,
          "putts": 2
        },
        {
          "playerId": "P4",
          "holeNumber": 8,
          "grossStrokes": 4,
          "putts": 2
        },
        {
          "playerId": "P1",
          "holeNumber": 9,
          "grossStrokes": 3,
          "putts": 2
        },
        {
          "playerId": "P2",
          "holeNumber": 9,
          "grossStrokes": 5,
          "putts": 2
        },
        {
          "playerId": "P3",
          "holeNumber": 9,
          "grossStrokes": 5,
          "putts": 2
        },
        {
          "playerId": "P4",
          "holeNumber": 9,
          "grossStrokes": 3,
          "putts": 2
        },
        {
          "playerId": "P1",
          "holeNumber": 10,
          "grossStrokes": 4,
          "putts": 2
        },
        {
          "playerId": "P2",
          "holeNumber": 10,
          "grossStrokes": 4,
          "putts": 2
        },
        {
          "playerId": "P3",
          "holeNumber": 10,
          "grossStrokes": 6,
          "putts": 2
        },
        {
          "playerId": "P4",
          "holeNumber": 10,
          "grossStrokes": 6,
          "putts": 2
        },
        {
          "playerId": "P1",
          "holeNumber": 11,
          "grossStrokes": 5,
          "putts": 2
        },
        {
          "playerId": "P2",
          "holeNumber": 11,
          "grossStrokes": 6,
          "putts": 2
        },
        {
          "playerId": "P3",
          "holeNumber": 11,
          "grossStrokes": 6,
          "putts": 2
        },
        {
          "playerId": "P4",
          "holeNumber": 11,
          "grossStrokes": 5,
          "putts": 2
        },
        {
          "playerId": "P1",
          "holeNumber": 12,
          "grossStrokes": 4,
          "putts": 2
        },
        {
          "playerId": "P2",
          "holeNumber": 12,
          "grossStrokes": 4,
          "putts": 2
        },
        {
          "playerId": "P3",
          "holeNumber": 12,
          "grossStrokes": 6,
          "putts": 2
        },
        {
          "playerId": "P4",
          "holeNumber": 12,
          "grossStrokes": 6,
          "putts": 2
        },
        {
          "playerId": "P1",
          "holeNumber": 13,
          "grossStrokes": 4,
          "putts": 2
        },
        {
          "playerId": "P2",
          "holeNumber": 13,
          "grossStrokes": 5,
          "putts": 2
        },
        {
          "playerId": "P3",
          "holeNumber": 13,
          "grossStrokes": 5,
          "putts": 2
        },
        {
          "playerId": "P4",
          "holeNumber": 13,
          "grossStrokes": 6,
          "putts": 2
        },
        {
          "playerId": "P1",
          "holeNumber": 14,
          "grossStrokes": 5,
          "putts": 2
        },
        {
          "playerId": "P2",
          "holeNumber": 14,
          "grossStrokes": 6,
          "putts": 2
        },
        {
          "playerId": "P3",
          "holeNumber": 14,
          "grossStrokes": 6,
          "putts": 2
        },
        {
          "playerId": "P4",
          "holeNumber": 14,
          "grossStrokes": 7,
          "putts": 2
        },
        {
          "playerId": "P1",
          "holeNumber": 15,
          "grossStrokes": 3,
          "putts": 2
        },
        {
          "playerId": "P2",
          "holeNumber": 15,
          "grossStrokes": 4,
          "putts": 2
        },
        {
          "playerId": "P3",
          "holeNumber": 15,
          "grossStrokes": 5,
          "putts": 2
        },
        {
          "playerId": "P4",
          "holeNumber": 15,
          "grossStrokes": 5,
          "putts": 2
        },
        {
          "playerId": "P1",
          "holeNumber": 16,
          "grossStrokes": 4,
          "putts": 2
        },
        {
          "playerId": "P2",
          "holeNumber": 16,
          "grossStrokes": 5,
          "putts": 2
        },
        {
          "playerId": "P3",
          "holeNumber": 16,
          "grossStrokes": 5,
          "putts": 2
        },
        {
          "playerId": "P4",
          "holeNumber": 16,
          "grossStrokes": 6,
          "putts": 2
        },
        {
          "playerId": "P1",
          "holeNumber": 17,
          "grossStrokes": 2,
          "putts": 2
        },
        {
          "playerId": "P2",
          "holeNumber": 17,
          "grossStrokes": 4,
          "putts": 2
        },
        {
          "playerId": "P3",
          "holeNumber": 17,
          "grossStrokes": 4,
          "putts": 2
        },
        {
          "playerId": "P4",
          "holeNumber": 17,
          "grossStrokes": 5,
          "putts": 2
        },
        {
          "playerId": "P1",
          "holeNumber": 18,
          "grossStrokes": 4,
          "putts": 2
        },
        {
          "playerId": "P2",
          "holeNumber": 18,
          "grossStrokes": 5,
          "putts": 2
        },
        {
          "playerId": "P3",
          "holeNumber": 18,
          "grossStrokes": 6,
          "putts": 2
        },
        {
          "playerId": "P4",
          "holeNumber": 18,
          "grossStrokes": 7,
          "putts": 2
        }
      ],
      "holeMeta": []
    },
    {
      "roundNumber": 3,
      "pairings": {
        "teamA": [
          "P1",
          "P4"
        ],
        "teamB": [
          "P2",
          "P3"
        ]
      },
      "holeScores": [
        {
          "playerId": "P1",
          "holeNumber": 1,
          "grossStrokes": 4,
          "putts": 2
        },
        {
          "playerId": "P2",
          "holeNumber": 1,
          "grossStrokes": 4,
          "putts": 2
        },
        {
          "playerId": "P3",
          "holeNumber": 1,
          "grossStrokes": 5,
          "putts": 2
        },
        {
          "playerId": "P4",
          "holeNumber": 1,
          "grossStrokes": 6,
          "putts": 2
        },
        {
          "playerId": "P1",
          "holeNumber": 2,
          "grossStrokes": 5,
          "putts": 2
        },
        {
          "playerId": "P2",
          "holeNumber": 2,
          "grossStrokes": 6,
          "putts": 2
        },
        {
          "playerId": "P3",
          "holeNumber": 2,
          "grossStrokes": 6,
          "putts": 2
        },
        {
          "playerId": "P4",
          "holeNumber": 2,
          "grossStrokes": 7,
          "putts": 2
        },
        {
          "playerId": "P1",
          "holeNumber": 3,
          "grossStrokes": 4,
          "putts": 2
        },
        {
          "playerId": "P2",
          "holeNumber": 3,
          "grossStrokes": 5,
          "putts": 2
        },
        {
          "playerId": "P3",
          "holeNumber": 3,
          "grossStrokes": 6,
          "putts": 2
        },
        {
          "playerId": "P4",
          "holeNumber": 3,
          "grossStrokes": 6,
          "putts": 2
        },
        {
          "playerId": "P1",
          "holeNumber": 4,
          "grossStrokes": 4,
          "putts": 2
        },
        {
          "playerId": "P2",
          "holeNumber": 4,
          "grossStrokes": 4,
          "putts": 2
        },
        {
          "playerId": "P3",
          "holeNumber": 4,
          "grossStrokes": 5,
          "putts": 2
        },
        {
          "playerId": "P4",
          "holeNumber": 4,
          "grossStrokes": 6,
          "putts": 2
        },
        {
          "playerId": "P1",
          "holeNumber": 5,
          "grossStrokes": 4,
          "putts": 2
        },
        {
          "playerId": "P2",
          "holeNumber": 5,
          "grossStrokes": 6,
          "putts": 2
        },
        {
          "playerId": "P3",
          "holeNumber": 5,
          "grossStrokes": 6,
          "putts": 2
        },
        {
          "playerId": "P4",
          "holeNumber": 5,
          "grossStrokes": 7,
          "putts": 2
        },
        {
          "playerId": "P1",
          "holeNumber": 6,
          "grossStrokes": 3,
          "putts": 2
        },
        {
          "playerId": "P2",
          "holeNumber": 6,
          "grossStrokes": 4,
          "putts": 2
        },
        {
          "playerId": "P3",
          "holeNumber": 6,
          "grossStrokes": 4,
          "putts": 2
        },
        {
          "playerId": "P4",
          "holeNumber": 6,
          "grossStrokes": 5,
          "putts": 2
        },
        {
          "playerId": "P1",
          "holeNumber": 7,
          "grossStrokes": 4,
          "putts": 2
        },
        {
          "playerId": "P2",
          "holeNumber": 7,
          "grossStrokes": 5,
          "putts": 2
        },
        {
          "playerId": "P3",
          "holeNumber": 7,
          "grossStrokes": 6,
          "putts": 2
        },
        {
          "playerId": "P4",
          "holeNumber": 7,
          "grossStrokes": 5,
          "putts": 2
        },
        {
          "playerId": "P1",
          "holeNumber": 8,
          "grossStrokes": 3,
          "putts": 2
        },
        {
          "playerId": "P2",
          "holeNumber": 8,
          "grossStrokes": 4,
          "putts": 2
        },
        {
          "playerId": "P3",
          "holeNumber": 8,
          "grossStrokes": 4,
          "putts": 2
        },
        {
          "playerId": "P4",
          "holeNumber": 8,
          "grossStrokes": 5,
          "putts": 2
        },
        {
          "playerId": "P1",
          "holeNumber": 9,
          "grossStrokes": 4,
          "putts": 2
        },
        {
          "playerId": "P2",
          "holeNumber": 9,
          "grossStrokes": 5,
          "putts": 2
        },
        {
          "playerId": "P3",
          "holeNumber": 9,
          "grossStrokes": 5,
          "putts": 2
        },
        {
          "playerId": "P4",
          "holeNumber": 9,
          "grossStrokes": 6,
          "putts": 2
        },
        {
          "playerId": "P1",
          "holeNumber": 10,
          "grossStrokes": 4,
          "putts": 2
        },
        {
          "playerId": "P2",
          "holeNumber": 10,
          "grossStrokes": 4,
          "putts": 2
        },
        {
          "playerId": "P3",
          "holeNumber": 10,
          "grossStrokes": 5,
          "putts": 2
        },
        {
          "playerId": "P4",
          "holeNumber": 10,
          "grossStrokes": 6,
          "putts": 2
        },
        {
          "playerId": "P1",
          "holeNumber": 11,
          "grossStrokes": 5,
          "putts": 2
        },
        {
          "playerId": "P2",
          "holeNumber": 11,
          "grossStrokes": 6,
          "putts": 2
        },
        {
          "playerId": "P3",
          "holeNumber": 11,
          "grossStrokes": 6,
          "putts": 2
        },
        {
          "playerId": "P4",
          "holeNumber": 11,
          "grossStrokes": 7,
          "putts": 2
        },
        {
          "playerId": "P1",
          "holeNumber": 12,
          "grossStrokes": 4,
          "putts": 2
        },
        {
          "playerId": "P2",
          "holeNumber": 12,
          "grossStrokes": 5,
          "putts": 2
        },
        {
          "playerId": "P3",
          "holeNumber": 12,
          "grossStrokes": 6,
          "putts": 2
        },
        {
          "playerId": "P4",
          "holeNumber": 12,
          "grossStrokes": 6,
          "putts": 2
        },
        {
          "playerId": "P1",
          "holeNumber": 13,
          "grossStrokes": 4,
          "putts": 2
        },
        {
          "playerId": "P2",
          "holeNumber": 13,
          "grossStrokes": 3,
          "putts": 2
        },
        {
          "playerId": "P3",
          "holeNumber": 13,
          "grossStrokes": 3,
          "putts": 2
        },
        {
          "playerId": "P4",
          "holeNumber": 13,
          "grossStrokes": 6,
          "putts": 2
        },
        {
          "playerId": "P1",
          "holeNumber": 14,
          "grossStrokes": 5,
          "putts": 2
        },
        {
          "playerId": "P2",
          "holeNumber": 14,
          "grossStrokes": 6,
          "putts": 2
        },
        {
          "playerId": "P3",
          "holeNumber": 14,
          "grossStrokes": 6,
          "putts": 2
        },
        {
          "playerId": "P4",
          "holeNumber": 14,
          "grossStrokes": 7,
          "putts": 2
        },
        {
          "playerId": "P1",
          "holeNumber": 15,
          "grossStrokes": 3,
          "putts": 2
        },
        {
          "playerId": "P2",
          "holeNumber": 15,
          "grossStrokes": 4,
          "putts": 2
        },
        {
          "playerId": "P3",
          "holeNumber": 15,
          "grossStrokes": 4,
          "putts": 2
        },
        {
          "playerId": "P4",
          "holeNumber": 15,
          "grossStrokes": 4,
          "putts": 2
        },
        {
          "playerId": "P1",
          "holeNumber": 16,
          "grossStrokes": 4,
          "putts": 2
        },
        {
          "playerId": "P2",
          "holeNumber": 16,
          "grossStrokes": 5,
          "putts": 2
        },
        {
          "playerId": "P3",
          "holeNumber": 16,
          "grossStrokes": 5,
          "putts": 2
        },
        {
          "playerId": "P4",
          "holeNumber": 16,
          "grossStrokes": 4,
          "putts": 2
        },
        {
          "playerId": "P1",
          "holeNumber": 17,
          "grossStrokes": 3,
          "putts": 2
        },
        {
          "playerId": "P2",
          "holeNumber": 17,
          "grossStrokes": 4,
          "putts": 2
        },
        {
          "playerId": "P3",
          "holeNumber": 17,
          "grossStrokes": 4,
          "putts": 2
        },
        {
          "playerId": "P4",
          "holeNumber": 17,
          "grossStrokes": 5,
          "putts": 2
        },
        {
          "playerId": "P1",
          "holeNumber": 18,
          "grossStrokes": 4,
          "putts": 2
        },
        {
          "playerId": "P2",
          "holeNumber": 18,
          "grossStrokes": 5,
          "putts": 2
        },
        {
          "playerId": "P3",
          "holeNumber": 18,
          "grossStrokes": 6,
          "putts": 2
        },
        {
          "playerId": "P4",
          "holeNumber": 18,
          "grossStrokes": 6,
          "putts": 2
        }
      ],
      "holeMeta": []
    },
    {
      "roundNumber": 4,
      "pairings": {
        "teamA": [
          "P1",
          "P2"
        ],
        "teamB": [
          "P3",
          "P4"
        ]
      },
      "holeScores": [
        {
          "playerId": "P1",
          "holeNumber": 1,
          "grossStrokes": 4,
          "putts": 2
        },
        {
          "playerId": "P2",
          "holeNumber": 1,
          "grossStrokes": 5,
          "putts": 2
        },
        {
          "playerId": "P3",
          "holeNumber": 1,
          "grossStrokes": 5,
          "putts": 2
        },
        {
          "playerId": "P4",
          "holeNumber": 1,
          "grossStrokes": 6,
          "putts": 2
        },
        {
          "playerId": "P1",
          "holeNumber": 2,
          "grossStrokes": 5,
          "putts": 2
        },
        {
          "playerId": "P2",
          "holeNumber": 2,
          "grossStrokes": 5,
          "putts": 2
        },
        {
          "playerId": "P3",
          "holeNumber": 2,
          "grossStrokes": 7,
          "putts": 2
        },
        {
          "playerId": "P4",
          "holeNumber": 2,
          "grossStrokes": 7,
          "putts": 2
        },
        {
          "playerId": "P1",
          "holeNumber": 3,
          "grossStrokes": 3,
          "putts": 2
        },
        {
          "playerId": "P2",
          "holeNumber": 3,
          "grossStrokes": 5,
          "putts": 2
        },
        {
          "playerId": "P3",
          "holeNumber": 3,
          "grossStrokes": 6,
          "putts": 2
        },
        {
          "playerId": "P4",
          "holeNumber": 3,
          "grossStrokes": 6,
          "putts": 2
        },
        {
          "playerId": "P1",
          "holeNumber": 4,
          "grossStrokes": 4,
          "putts": 2
        },
        {
          "playerId": "P2",
          "holeNumber": 4,
          "grossStrokes": 5,
          "putts": 2
        },
        {
          "playerId": "P3",
          "holeNumber": 4,
          "grossStrokes": 5,
          "putts": 2
        },
        {
          "playerId": "P4",
          "holeNumber": 4,
          "grossStrokes": 6,
          "putts": 2
        },
        {
          "playerId": "P1",
          "holeNumber": 5,
          "grossStrokes": 5,
          "putts": 2
        },
        {
          "playerId": "P2",
          "holeNumber": 5,
          "grossStrokes": 6,
          "putts": 2
        },
        {
          "playerId": "P3",
          "holeNumber": 5,
          "grossStrokes": 6,
          "putts": 2
        },
        {
          "playerId": "P4",
          "holeNumber": 5,
          "grossStrokes": 7,
          "putts": 2
        },
        {
          "playerId": "P1",
          "holeNumber": 6,
          "grossStrokes": 3,
          "putts": 2
        },
        {
          "playerId": "P2",
          "holeNumber": 6,
          "grossStrokes": 4,
          "putts": 2
        },
        {
          "playerId": "P3",
          "holeNumber": 6,
          "grossStrokes": 4,
          "putts": 2
        },
        {
          "playerId": "P4",
          "holeNumber": 6,
          "grossStrokes": 5,
          "putts": 2
        },
        {
          "playerId": "P1",
          "holeNumber": 7,
          "grossStrokes": 4,
          "putts": 2
        },
        {
          "playerId": "P2",
          "holeNumber": 7,
          "grossStrokes": 5,
          "putts": 2
        },
        {
          "playerId": "P3",
          "holeNumber": 7,
          "grossStrokes": 6,
          "putts": 2
        },
        {
          "playerId": "P4",
          "holeNumber": 7,
          "grossStrokes": 6,
          "putts": 2
        },
        {
          "playerId": "P1",
          "holeNumber": 8,
          "grossStrokes": 3,
          "putts": 2
        },
        {
          "playerId": "P2",
          "holeNumber": 8,
          "grossStrokes": 4,
          "putts": 2
        },
        {
          "playerId": "P3",
          "holeNumber": 8,
          "grossStrokes": 4,
          "putts": 2
        },
        {
          "playerId": "P4",
          "holeNumber": 8,
          "grossStrokes": 4,
          "putts": 2
        },
        {
          "playerId": "P1",
          "holeNumber": 9,
          "grossStrokes": 4,
          "putts": 2
        },
        {
          "playerId": "P2",
          "holeNumber": 9,
          "grossStrokes": 5,
          "putts": 2
        },
        {
          "playerId": "P3",
          "holeNumber": 9,
          "grossStrokes": 5,
          "putts": 2
        },
        {
          "playerId": "P4",
          "holeNumber": 9,
          "grossStrokes": 6,
          "putts": 2
        },
        {
          "playerId": "P1",
          "holeNumber": 10,
          "grossStrokes": 4,
          "putts": 2
        },
        {
          "playerId": "P2",
          "holeNumber": 10,
          "grossStrokes": 5,
          "putts": 2
        },
        {
          "playerId": "P3",
          "holeNumber": 10,
          "grossStrokes": 5,
          "putts": 2
        },
        {
          "playerId": "P4",
          "holeNumber": 10,
          "grossStrokes": 6,
          "putts": 2
        },
        {
          "playerId": "P1",
          "holeNumber": 11,
          "grossStrokes": 4,
          "putts": 2
        },
        {
          "playerId": "P2",
          "holeNumber": 11,
          "grossStrokes": 6,
          "putts": 2
        },
        {
          "playerId": "P3",
          "holeNumber": 11,
          "grossStrokes": 7,
          "putts": 2
        },
        {
          "playerId": "P4",
          "holeNumber": 11,
          "grossStrokes": 6,
          "putts": 2
        },
        {
          "playerId": "P1",
          "holeNumber": 12,
          "grossStrokes": 4,
          "putts": 2
        },
        {
          "playerId": "P2",
          "holeNumber": 12,
          "grossStrokes": 5,
          "putts": 2
        },
        {
          "playerId": "P3",
          "holeNumber": 12,
          "grossStrokes": 5,
          "putts": 2
        },
        {
          "playerId": "P4",
          "holeNumber": 12,
          "grossStrokes": 6,
          "putts": 2
        },
        {
          "playerId": "P1",
          "holeNumber": 13,
          "grossStrokes": 4,
          "putts": 2
        },
        {
          "playerId": "P2",
          "holeNumber": 13,
          "grossStrokes": 5,
          "putts": 2
        },
        {
          "playerId": "P3",
          "holeNumber": 13,
          "grossStrokes": 5,
          "putts": 2
        },
        {
          "playerId": "P4",
          "holeNumber": 13,
          "grossStrokes": 6,
          "putts": 2
        },
        {
          "playerId": "P1",
          "holeNumber": 14,
          "grossStrokes": 5,
          "putts": 2
        },
        {
          "playerId": "P2",
          "holeNumber": 14,
          "grossStrokes": 6,
          "putts": 2
        },
        {
          "playerId": "P3",
          "holeNumber": 14,
          "grossStrokes": 7,
          "putts": 2
        },
        {
          "playerId": "P4",
          "holeNumber": 14,
          "grossStrokes": 7,
          "putts": 2
        },
        {
          "playerId": "P1",
          "holeNumber": 15,
          "grossStrokes": 3,
          "putts": 2
        },
        {
          "playerId": "P2",
          "holeNumber": 15,
          "grossStrokes": 4,
          "putts": 2
        },
        {
          "playerId": "P3",
          "holeNumber": 15,
          "grossStrokes": 4,
          "putts": 2
        },
        {
          "playerId": "P4",
          "holeNumber": 15,
          "grossStrokes": 5,
          "putts": 2
        },
        {
          "playerId": "P1",
          "holeNumber": 16,
          "grossStrokes": 4,
          "putts": 2
        },
        {
          "playerId": "P2",
          "holeNumber": 16,
          "grossStrokes": 5,
          "putts": 2
        },
        {
          "playerId": "P3",
          "holeNumber": 16,
          "grossStrokes": 5,
          "putts": 2
        },
        {
          "playerId": "P4",
          "holeNumber": 16,
          "grossStrokes": 6,
          "putts": 2
        },
        {
          "playerId": "P1",
          "holeNumber": 17,
          "grossStrokes": 3,
          "putts": 2
        },
        {
          "playerId": "P2",
          "holeNumber": 17,
          "grossStrokes": 4,
          "putts": 2
        },
        {
          "playerId": "P3",
          "holeNumber": 17,
          "grossStrokes": 4,
          "putts": 2
        },
        {
          "playerId": "P4",
          "holeNumber": 17,
          "grossStrokes": 5,
          "putts": 2
        },
        {
          "playerId": "P1",
          "holeNumber": 18,
          "grossStrokes": 4,
          "putts": 2
        },
        {
          "playerId": "P2",
          "holeNumber": 18,
          "grossStrokes": 5,
          "putts": 2
        },
        {
          "playerId": "P3",
          "holeNumber": 18,
          "grossStrokes": 5,
          "putts": 2
        },
        {
          "playerId": "P4",
          "holeNumber": 18,
          "grossStrokes": 6,
          "putts": 2
        }
      ],
      "holeMeta": []
    }
  ],
  "bets": [
    {
      "id": "BET1",
      "playerAId": "P1",
      "playerBId": "P4",
      "betType": "match_play_per_hole",
      "stakePerHoleCents": 50,
      "config": {},
      "applicableRounds": [
        1,
        2,
        3,
        4
      ]
    },
    {
      "id": "BET2",
      "playerAId": "P2",
      "playerBId": "P3",
      "betType": "match_play_per_hole",
      "stakePerHoleCents": 50,
      "config": {},
      "applicableRounds": [
        1,
        2
      ]
    }
  ],
  "bestBallConfig": {
    "basePerHoleCents": 100,
    "sandies": false,
    "sandiesBonusPerHoleCents": 0,
    "greenieCarryover": false,
    "greenieValidation": "none",
    "greenieBaseCents": 0
  },
  "skinsConfig": {
    "mode": "gross",
    "buyInPerParticipantCents": 500,
    "lastHoleUnclaimedResolution": "split-among-winners"
  },
  "expected": {
    "verifiedBy": null,
    "verifiedDate": null,
    "matrixCents": null,
    "totalsCents": null,
    "skinsResults": null,
    "betResults": null,
    "_handCalcWorksheet": "TODO: walk per-round per-rule contributions; sum into matrixCents; verify zero-sum; sign verifiedBy + verifiedDate (YYYY-MM-DD)."
  }
}